pichi/__init__.py
pichi/bloom.py
pichi/classes.py
pichi/starter.py
pichi/utils.py
pichi/version.py
pichi-0.3.6.dist-info/LICENSE.txt
pichi-0.3.6.dist-info/METADATA
pichi-0.3.6.dist-info/WHEEL
pichi-0.3.6.dist-info/entry_points.txt
pichi-0.3.6.dist-info/top_level.txt
pichi-0.3.6.dist-info/RECORD
