Metadata-Version: 2.1
Name: pichi
Version: 0.3.6
Summary: A utility for generating simple pcap indexes
Home-page: https://bitbucket.org/c0nch0b4r/pichi
Author: c0nch0b4r
Author-email: lp1.on.fire@gmail.com
License: UNKNOWN
Download-URL: https://bitbucket.org/c0nch0b4r/pichi/get/0.3.6.tar.gz
Project-URL: Source, https://bitbucket.org/c0nch0b4r/pichi/src
Keywords: pcap indexer
Platform: UNKNOWN
Classifier: Environment :: Console
Classifier: Intended Audience :: Information Technology
Classifier: License :: OSI Approved :: GNU General Public License v3 or later (GPLv3+)
Classifier: Natural Language :: English
Classifier: Operating System :: OS Independent
Classifier: Programming Language :: Python :: 3.6
Classifier: Programming Language :: Python :: 3.7
Requires-Python: >=3.6, <4
Requires-Dist: typing
